markopolo.py
markopolo-2020.4.26.dist-info/LICENSE
markopolo-2020.4.26.dist-info/METADATA
markopolo-2020.4.26.dist-info/WHEEL
markopolo-2020.4.26.dist-info/top_level.txt
markopolo-2020.4.26.dist-info/RECORD
