Metadata-Version: 2.1
Name: markopolo
Version: 2020.4.26
Summary: Markup Language Parser
Home-page: https://github.com/hackerassist/markopolo
Author: Raja Simon
License: MIT
Platform: UNKNOWN
Classifier: License :: OSI Approved :: MIT License
Classifier: Programming Language :: Python
Classifier: Programming Language :: Python :: 3.6
Classifier: Programming Language :: Python :: Implementation :: CPython
Classifier: Programming Language :: Python :: Implementation :: PyPy
Requires-Python: >=3.6.0
